{
  "monitoring_id": 153,
  "timestamp": "20250811_204348_140",
  "analysis_method": "OCR_Rectangle",
  "result": {
    "full_text": "權志龍 收賊鞋6-10屬10/25/60/150/400龍天拳85-87攻15|25|45拳套10%10雪",
    "is_match": false,
    "player_name": "權志龍",
    "channel_number": "150",
    "matched_items": [],
    "matched_keywords": [],
    "confidence": 0.8217223960497968,
    "analysis_method": "OCR_Rectangle"
  },
  "raw_response": {
    "front_text": "權志龍",
    "rear_text": "收賊鞋6-10屬10/25/60/150/400龍天拳85-87攻15|25|45拳套10%10雪",
    "full_text": "權志龍 收賊鞋6-10屬10/25/60/150/400龍天拳85-87攻15|25|45拳套10%10雪",
    "ocr_results": [
      {
        "text": "權志龍",
        "confidence": 0.992142828608355,
        "bbox": [
          [
            8,
            4
          ],
          [
            80,
            4
          ],
          [
            80,
            36
          ],
          [
            8,
            36
          ]
        ]
      },
      {
        "text": "收賊鞋6-10屬10/25/60/150/400龍天拳85-87攻15|25|45拳套10%10雪",
        "confidence": 0.6513019634912385,
        "bbox": [
          [
            161,
            1
          ],
          [
            835,
            1
          ],
          [
            835,
            36
          ],
          [
            161,
            36
          ]
        ]
      }
    ],
    "white_rectangles": [
      [
        76,
        5,
        75,
        23
      ]
    ]
  },
  "screenshot_path": "monitoring_session_20250811_203702\\monitor_153_20250811_204347_501.png"
}