{
  "monitoring_id": 46,
  "timestamp": "20250811_203903_338",
  "analysis_method": "OCR_Rectangle",
  "result": {
    "full_text": "妹妹的情竇初開之繼母誘惑處男的我 收乾淨90弩 AD93 35雪 收弩攻捲10%只收10% 1:1雪",
    "is_match": false,
    "player_name": "妹妹的情竇初開之繼母誘惑處男的我",
    "channel_number": "未知",
    "matched_items": [],
    "matched_keywords": [],
    "confidence": 0.9340786261627041,
    "analysis_method": "OCR_Rectangle"
  },
  "raw_response": {
    "front_text": "妹妹的情竇初開之繼母誘惑處男的我",
    "rear_text": "收乾淨90弩 AD93 35雪 收弩攻捲10%只收10% 1:1雪",
    "full_text": "妹妹的情竇初開之繼母誘惑處男的我 收乾淨90弩 AD93 35雪 收弩攻捲10%只收10% 1:1雪",
    "ocr_results": [
      {
        "text": "妹妹的情竇初開之繼母誘惑處男的我",
        "confidence": 0.9927450117010557,
        "bbox": [
          [
            7,
            1
          ],
          [
            349,
            1
          ],
          [
            349,
            36
          ],
          [
            7,
            36
          ]
        ]
      },
      {
        "text": "收乾淨90弩 AD93 35雪 收弩攻捲10%只收10% 1:1雪",
        "confidence": 0.8754122406243525,
        "bbox": [
          [
            428,
            4
          ],
          [
            926,
            4
          ],
          [
            926,
            36
          ],
          [
            428,
            36
          ]
        ]
      }
    ],
    "white_rectangles": [
      [
        344,
        5,
        74,
        23
      ]
    ]
  },
  "screenshot_path": "monitoring_session_20250811_203702\\monitor_046_20250811_203902_647.png"
}