{
  "monitoring_id": 152,
  "timestamp": "20250811_204345_433",
  "analysis_method": "OCR_Rectangle",
  "result": {
    "full_text": "州州州 收怪物包 私訊",
    "is_match": false,
    "player_name": "州州州",
    "channel_number": "未知",
    "matched_items": [],
    "matched_keywords": [],
    "confidence": 0.8932060745893496,
    "analysis_method": "OCR_Rectangle"
  },
  "raw_response": {
    "front_text": "州州州",
    "rear_text": "收怪物包 私訊",
    "full_text": "州州州 收怪物包 私訊",
    "ocr_results": [
      {
        "text": "州州州",
        "confidence": 0.999801234558203,
        "bbox": [
          [
            8,
            4
          ],
          [
            82,
            4
          ],
          [
            82,
            34
          ],
          [
            8,
            34
          ]
        ]
      },
      {
        "text": "收怪物包 私訊",
        "confidence": 0.7866109146204963,
        "bbox": [
          [
            161,
            4
          ],
          [
            310,
            4
          ],
          [
            310,
            36
          ],
          [
            161,
            36
          ]
        ]
      }
    ],
    "white_rectangles": [
      [
        76,
        5,
        75,
        23
      ]
    ]
  },
  "screenshot_path": "monitoring_session_20250811_203702\\monitor_152_20250811_204345_099.png"
}