{
  "monitoring_id": 3,
  "timestamp": "20250811_203708_288",
  "analysis_method": "OCR_Rectangle",
  "result": {
    "full_text": "瘋齧 出臉敏10%報价",
    "is_match": false,
    "player_name": "瘋齧",
    "channel_number": "未知",
    "matched_items": [],
    "matched_keywords": [],
    "confidence": 0.5744175609463422,
    "analysis_method": "OCR_Rectangle"
  },
  "raw_response": {
    "front_text": "瘋齧",
    "rear_text": "出臉敏10%報价",
    "full_text": "瘋齧 出臉敏10%報价",
    "ocr_results": [
      {
        "text": "瘋齧",
        "confidence": 0.17788298540689815,
        "bbox": [
          [
            8,
            4
          ],
          [
            58,
            4
          ],
          [
            58,
            34
          ],
          [
            8,
            34
          ]
        ]
      },
      {
        "text": "出臉敏10%報价",
        "confidence": 0.9709521364857864,
        "bbox": [
          [
            142,
            4
          ],
          [
            296,
            4
          ],
          [
            296,
            36
          ],
          [
            142,
            36
          ]
        ]
      }
    ],
    "white_rectangles": [
      [
        56,
        5,
        75,
        23
      ]
    ]
  },
  "screenshot_path": "monitoring_session_20250811_203702\\monitor_003_20250811_203708_012.png"
}